{
 "Osiedle Armii Krajowej": {
  "dzielnica": "Rataje", 
  "kody_pocztowe": "61-373,61-374,61-375,61-376,61-377,61-378,61-379,61-381", 
  "numeracja": "1-95, 97-98, 100-102, 105, 107-150"
 }, 
 "Osiedle Bohater\u00f3w II Wojny \u015awiatowej": {
  "dzielnica": "Rataje", 
  "kody_pocztowe": "61-382,61-383,61-384,61-385,61-386,61-387,61-388", 
  "numeracja": "1-86, 88"
 }, 
 "Osiedle Boles\u0142awa Chrobrego": {
  "dzielnica": "Pi\u0105tkowo", 
  "kody_pocztowe": "60-681", 
  "numeracja": "1-41, 46-48, 101-102, 104-110, 116-119, 121-122"
 }, 
 "Osiedle Boles\u0142awa \u015amia\u0142ego": {
  "dzielnica": "Pi\u0105tkowo", 
  "kody_pocztowe": "60-681,60-682", 
  "numeracja": "1-41, 101, 104-110, 121-122"
 }, 
 "Osiedle Czecha": {
  "dzielnica": "Chartowo", 
  "kody_pocztowe": "61-286,61-287,61-288,61-289,61-290,61-291,61-292,61-298", 
  "numeracja": "5-59, 61-73, 75-108, 110-111, 114-140"
 }, 
 "Osiedle D\u0119bina": {
  "dzielnica": "Zielony D\u0119biec", 
  "kody_pocztowe": "61-450", 
  "numeracja": "1-11, 16-23, 101-107"
 }, 
 "Osiedle Jagiello\u0144skie": {
  "dzielnica": "Rataje", 
  "kody_pocztowe": "61-217,61-218,61-219,61-221,61-222,61-223,61-224,61-225,61-226,61-227,61-228,61-229,61-231,61-233,61-234,61-235,61-236,61-237,61-238,61-239,61-241", 
  "numeracja": "1-9, 12, 14-26, 31-130"
 }, 
 "Osiedle Jana III Sobieskiego": {
  "dzielnica": "Jana III Sobieskiego i Marysie\u0144ki", 
  "kody_pocztowe": "60-688", 
  "numeracja": "1-45, 52, 102-106, 108-109, 112, 114-118"
 }, 
 "Osiedle Kosmonaut\u00f3w": {
  "dzielnica": "Nowe Winogrady Wsch\u00f3d", 
  "kody_pocztowe": "61-621,61-624,61-627,61-631,61-639,61-641,61-642", 
  "numeracja": "1-25, 102, 104, 106-108, 110-111, 118, 120"
 }, 
 "Osiedle Lecha": {
  "dzielnica": "Chartowo", 
  "kody_pocztowe": "61-293,61-294,61-295,61-296,61-297,61-298,61-299", 
  "numeracja": "2-37, 39-40, 42-129"
 }, 
 "Osiedle Lotnictwa Polskiego": {
  "dzielnica": "Wola", 
  "kody_pocztowe": "60-406", 
  "numeracja": "6-11, 13-16, 109"
 }, 
 "Osiedle Marysie\u0144ki": {
  "dzielnica": "Jana III Sobieskiego i Marysie\u0144ki", 
  "kody_pocztowe": "60-683", 
  "numeracja": "25"
 }, 
 "Osiedle Na Murawie": {
  "dzielnica": "Stare Winogrady", 
  "kody_pocztowe": "61-655", 
  "numeracja": "3-13"
 }, 
 "Osiedle Or\u0142a Bia\u0142ego": {
  "dzielnica": "\u017begrze", 
  "kody_pocztowe": "61-251", 
  "numeracja": "1, 3-72, 74-86, 89-103, 105-121"
 }, 
 "Osiedle O\u015bwiecenia": {
  "dzielnica": "Rataje", 
  "kody_pocztowe": "61-205,61-206,61-207,61-208,61-209,61-211,61-212", 
  "numeracja": "1-27, 29-57, 59-62, 64-112"
 }, 
 "Osiedle Piastowskie": {
  "dzielnica": "Rataje", 
  "kody_pocztowe": "61-146,61-147,61-148,61-149,61-151,61-152,61-153,61-154,61-155,61-156,61-157,61-158,61-159,61-161,61-162,61-163,61-164,61-165,61-166", 
  "numeracja": "2-36, 40, 42-79, 81-115, 117-120"
 }, 
 "Osiedle Pod Lipami": {
  "dzielnica": "Nowe Winogrady Po\u0142udnie", 
  "kody_pocztowe": "61-628,61-629,61-632,61-633,61-634,61-635,61-636,61-637,61-638", 
  "numeracja": "1-17, 100-104, 106-108"
 }, 
 "Osiedle Polan": {
  "dzielnica": "\u017begrze", 
  "kody_pocztowe": "61-253", 
  "numeracja": "1-54, 100"
 }, 
 "Osiedle Powsta\u0144 Narodowych": {
  "dzielnica": "Rataje", 
  "kody_pocztowe": "61-213,61-214,61-215,61-216", 
  "numeracja": "1, 3-28, 31-37, 39-62"
 }, 
 "Osiedle Powsta\u0144c\u00f3w Warszawy": {
  "dzielnica": "Winiary", 
  "kody_pocztowe": "61-656", 
  "numeracja": "1-9"
 }, 
 "Osiedle Przemys\u0142awa": {
  "dzielnica": "Antoninek-Zieliniec-Kobylepole", 
  "kody_pocztowe": "61-064", 
  "numeracja": "1-26, 101-102"
 }, 
 "Osiedle Przyja\u017ani": {
  "dzielnica": "Nowe Winogrady Po\u0142udnie", 
  "kody_pocztowe": "61-679,61-681,61-682,61-683,61-684,61-685,61-686,61-687,61-688,61-689", 
  "numeracja": "1-24, 115-118, 120, 125-127, 129, 132-137, 141-142"
 }, 
 "Osiedle Rusa": {
  "dzielnica": "Chartowo", 
  "kody_pocztowe": "61-245", 
  "numeracja": "1-13, 15-59, 62-138"
 }, 
 "Osiedle Rzeczypospolitej": {
  "dzielnica": "Rataje", 
  "kody_pocztowe": "61-383,61-389,61-392,61-393,61-394,61-395,61-396,61-397", 
  "numeracja": "1, 3-4, 6-14, 16-111"
 }, 
 "Osiedle Stare \u017begrze": {
  "dzielnica": "\u017begrze", 
  "kody_pocztowe": "61-248,61-249", 
  "numeracja": "1-15, 18-79, 81, 84-87, 89, 92-112, 114-120, 122-128, 130-151, 161-174, 176-185, 187-189"
 }, 
 "Osiedle Stefana Batorego": {
  "dzielnica": "Pi\u0105tkowo", 
  "kody_pocztowe": "60-687", 
  "numeracja": "1-55, 57-59, 64-70, 73-82, 101, 113"
 }, 
 "Osiedle Tysi\u0105clecia": {
  "dzielnica": "Chartowo", 
  "kody_pocztowe": "61-255", 
  "numeracja": "3-14, 16-30, 33-43, 45-66, 69-73"
 }, 
 "Osiedle Wichrowe Wzg\u00f3rze": {
  "dzielnica": "Nowe Winogrady P\u00f3\u0142noc", 
  "kody_pocztowe": "61-672,61-673,61-674,61-675,61-676,61-677,61-678,61-697,61-698,61-699", 
  "numeracja": "2-36, 103-106, 111-112, 114, 118-124, 128, 130"
 }, 
 "Osiedle Winiary": {
  "dzielnica": "Winiary", 
  "kody_pocztowe": "60-665", 
  "numeracja": "1-4, 6-54"
 }, 
 "Osiedle W\u0142adys\u0142awa Jagie\u0142\u0142y": {
  "dzielnica": "Pi\u0105tkowo", 
  "kody_pocztowe": "60-688,60-694", 
  "numeracja": "1-29, 33, 103, 105-106, 231"
 }, 
 "Osiedle W\u0142adys\u0142awa \u0141okietka": {
  "dzielnica": "Naramowice", 
  "kody_pocztowe": "61-616", 
  "numeracja": "1-14, 102, 104, 115"
 }, 
 "Osiedle Zwyci\u0119stwa": {
  "dzielnica": "Nowe Winogrady P\u00f3\u0142noc", 
  "kody_pocztowe": "61-643,61-644,61-645,61-646,61-647,61-648,61-649,61-650,61-651,61-652,61-653", 
  "numeracja": "1-26, 28, 101-102, 108-114, 116-118, 123, 125"
 }, 
 "Osiedle Zygmunta Starego": {
  "dzielnica": "Pi\u0105tkowo", 
  "kody_pocztowe": "60-684", 
  "numeracja": "4, 6-9, 12-17"
 }
}