{"1":{"petle":[],"przystanki":[],"czas":false},"2":{"petle":["Ogrody","Dębiec"],"przystanki":[],"czas":33},"3":{"petle":["Zawady","Wilczak"],"przystanki":[],"czas":24},"4":{"petle":["Połabska","Starołęka"],"przystanki":[],"czas":41},"5":{"petle":["Piątkowska","Stomil"],"przystanki":[],"czas":41},"6":{"petle":["Franowo","Miłostowo"],"przystanki":[],"czas":62},"7":{"petle":["Ogrody","Zawady"],"przystanki":[],"czas":35},"8":{"petle":["Osiedle Jana III Sobieskiego","Miłostowo"],"przystanki":[],"czas":29},"9":{"petle":["Piątkowska","Dębiec"],"przystanki":[],"czas":38},"10":{"petle":["Połabska","Dębiec"],"przystanki":[],"czas":43},"11":{"petle":["Ogrody","Starołęka"],"przystanki":[],"czas":36},"12":{"petle":["Starołęka","Osiedle Jana III Sobieskiego"],"przystanki":[],"czas":35},"13":{"petle":[],"przystanki":[],"czas":false},"14":{"petle":["Osiedle Jana III Sobieskiego","Zajezdnia Głogowska"],"przystanki":[],"czas":36},"15":{"petle":["Starołęka","Osiedle Jana III Sobieskiego"],"przystanki":[],"czas":49},"16":{"petle":["Franowo","Osiedle Jana III Sobieskiego"],"przystanki":[],"czas":33},"17":{"petle":["Starołęka","Ogrody"],"przystanki":[],"czas":42},"18":{"petle":["Franowo","Zajezdnia Głogowska"],"przystanki":[],"czas":32},"19":{"petle":[],"przystanki":[],"czas":false},"20":{"petle":[],"przystanki":[],"czas":false},"21":{"petle":[],"przystanki":[],"czas":false},"22":{"petle":[],"przystanki":[],"czas":false},"23":{"petle":[],"przystanki":[],"czas":false},"24":{"petle":[],"przystanki":[],"czas":false},"25":{"petle":["Węgorka","Zajezdnia Głogowska"],"przystanki":[],"czas":24},"26":{"petle":[],"przystanki":[],"czas":false},"27":{"petle":[],"przystanki":[],"czas":false},"28":{"petle":[],"przystanki":[],"czas":false},"29":{"petle":[],"przystanki":[],"czas":false},"40":{"petle":[],"przystanki":[],"czas":false},"41":{"petle":[],"przystanki":[],"czas":false},"42":{"petle":[],"przystanki":[],"czas":false},"43":{"petle":[],"przystanki":[],"czas":false},"44":{"petle":[],"przystanki":[],"czas":false},"45":{"petle":["Rondo Kaponiera","Kacza"],"przystanki":[],"czas":21},"46":{"petle":["Strzeszyn","Boranta"],"przystanki":[],"czas":28},"47":{"petle":["Boranta","Chwaliszewo"],"przystanki":[],"czas":20},"48":{"petle":["Ławica","Rondo Kaponiera"],"przystanki":[],"czas":23},"49":{"petle":["Azaliowa","Górczyn Dworzec"],"przystanki":[],"czas":15},"50":{"petle":["Górczyn Dworzec","Ogrody"],"przystanki":[],"czas":24},"51":{"petle":["Sobieskiego Dworzec","Dworzec Główny"],"przystanki":[],"czas":37},"52":{"petle":["Darzybór","Rataje Dworzec"],"przystanki":[],"czas":25},"53":{"petle":["Świątniczki","Franowo"],"przystanki":[],"czas":28},"54":{"petle":["Spławie","Franowo"],"przystanki":[],"czas":18},"55":{"petle":["Zalasewo/Planetarna","Rataje Dworzec"],"przystanki":[],"czas":30},"56":{"petle":[],"przystanki":[],"czas":false},"57":{"petle":["Nowe Zoo","Śródka Dworzec"],"przystanki":[],"czas":28},"58":{"petle":["Sypniewo","Starołęka Dworzec"],"przystanki":[],"czas":18},"59":{"petle":["Port Lotniczy Ławica","Rondo Kaponiera"],"przystanki":[],"czas":18},"60":{"petle":["Strzeszyn","Garbary Dworzec"],"przystanki":[],"czas":33},"61":{"petle":["Krzyżowniki","Ogrody"],"przystanki":[],"czas":17},"62":{"petle":["Rataje Dworzec"],"przystanki":[],"czas":43},"63":{"petle":["Garbary Dworzec","Górczyn Dworzec"],"przystanki":[],"czas":35},"64":{"petle":["Puszkina","Kacza"],"przystanki":[],"czas":41},"65":{"petle":["Starołęka","Rataje Dworzec"],"przystanki":[],"czas":17},"66":{"petle":["Zieliniec","Rataje Dworzec"],"przystanki":[],"czas":31},"67":{"petle":["Radojewo","Śródka Dworzec"],"przystanki":[],"czas":28},"68":{"petle":["Podolany","Dworzec Główny"],"przystanki":[],"czas":27},"69":{"petle":["Osiedle Kopernika","Osiedle Łokietka"],"przystanki":[],"czas":42},"70":{"petle":["Koziegłowy/Zakłady Drobiarskie","Śródka Dworzec"],"przystanki":[],"czas":22},"71":{"petle":["Osiedle Wichrowe Wzgórze","Osiedle Dębina"],"przystanki":[],"czas":42},"72":{"petle":["Koziegłowy/Osiedle Leśne","Piątkowska"],"przystanki":[],"czas":25},"73":{"petle":["Janikowo/Ogrodnicza","Śródka Dworzec"],"przystanki":[],"czas":26},"74":{"petle":["Osiedle Orła Białego","Sobieskiego Dworzec"],"przystanki":[],"czas":44},"75":{"petle":["Dębiec","Górczyn Dworzec"],"przystanki":[],"czas":14},"76":{"petle":["Osiedle Dębina","Plac Bernardyński"],"przystanki":[],"czas":16},"77":{"petle":["Osiedle Kwiatowe","Rondo Kaponiera"],"przystanki":[],"czas":32},"78":{"petle":["Śródka Dworzec","Szarych Szeregów"],"przystanki":[],"czas":32},"79":{"petle":["Dębiec","Kacza"],"przystanki":[],"czas":23},"80":{"petle":["Auchan/Sycowska","Górczyn Dworzec"],"przystanki":[],"czas":18},"81":{"petle":["M1 Centrum Handlowe","Rataje Dworzec"],"przystanki":[],"czas":17},"82":{"petle":["Osiedle Wichrowe Wzgórze","Górczyn Dworzec"],"przystanki":[],"czas":39},"83":{"petle":["Szarych Szeregów","Śródka Dworzec"],"przystanki":[],"czas":35},"84":{"petle":["Rataje Dworzec","Śródka Dworzec"],"przystanki":[],"czas":34},"85":{"petle":["Sobieskiego Dworzec","Śródka Dworzec"],"przystanki":[],"czas":36},"86":{"petle":["Kiekrz","Ogrody"],"przystanki":[],"czas":27},"87":{"petle":["Osiedle Różany Potok","Piątkowska"],"przystanki":[],"czas":16},"88":{"petle":[],"przystanki":[],"czas":false},"89":{"petle":["Starołęka Dworzec"],"przystanki":[],"czas":20},"90":{"petle":["Kazimierza Wielkiego","Sobieskiego Dworzec"],"przystanki":[],"czas":33},"91":{"petle":["Sobieskiego Dworzec","Osiedle Kopernika"],"przystanki":[],"czas":40},"92":{"petle":["Giełda Ogrodnicza Franowo","Rataje Dworzec"],"przystanki":[],"czas":16},"93":{"petle":["Sobieskiego Dworzec","Górczyn Dworzec"],"przystanki":[],"czas":33},"94":{"petle":["Starołęka Dworzec"],"przystanki":[],"czas":21},"95":{"petle":["Kiekrz","Ogrody"],"przystanki":[],"czas":28},"96":{"petle":["Rataje Dworzec"],"przystanki":[],"czas":41},"97":{"petle":["Osiedle Rusa Szpital","Rataje Dworzec"],"przystanki":[],"czas":14},"98":{"petle":["Osiedle Różany Potok","Sobieskiego Dworzec"],"przystanki":[],"czas":11},"99":{"petle":[],"przystanki":[],"czas":false},"100":{"petle":[],"przystanki":[],"czas":false},"231":{"petle":["Rondo Rataje","Rondo Kaponiera"],"przystanki":[],"czas":8},"232":{"petle":["Osiedle Rusa","Rondo Kaponiera"],"przystanki":[],"czas":18},"233":{"petle":["Zieliniec","Rondo Kaponiera"],"przystanki":[],"czas":21},"234":{"petle":["Dworzec Główny","Osiedle Batorego II"],"przystanki":[],"czas":22},"235":{"petle":["Sobieskiego Dworzec","Dworzec Główny"],"przystanki":[],"czas":23},"236":{"petle":["Dworzec Główny"],"przystanki":[],"czas":44},"237":{"petle":["Koziegłowy/Osiedle Leśne","Starołęka"],"przystanki":[],"czas":29},"238":{"petle":["Osiedle Orła Białego","Rondo Kaponiera"],"przystanki":[],"czas":19},"239":{"petle":["Kiekrz","Dworzec Główny"],"przystanki":[],"czas":27},"240":{"petle":["Kacza","Dworzec Główny"],"przystanki":[],"czas":21},"241":{"petle":[],"przystanki":[],"czas":false},"242":{"petle":["Port Lotniczy Ławica","Dworzec Główny"],"przystanki":[],"czas":21},"243":{"petle":["Dworzec Główny","Luboń/Kręta"],"przystanki":[],"czas":38},"244":{"petle":["Rataje Dworzec"],"przystanki":[],"czas":29},"245":{"petle":["Starołęka","Mogileńska"],"przystanki":[],"czas":24},"246":{"petle":["Dworzec Główny"],"przystanki":[],"czas":44},"247":{"petle":["Sypniewo","Rataje Dworzec"],"przystanki":[],"czas":26},"248":{"petle":["Radojewo","Sobieskiego Dworzec"],"przystanki":[],"czas":19},"249":{"petle":["Rondo Kaponiera","Dębiec"],"przystanki":[],"czas":23},"250":{"petle":[],"przystanki":[],"czas":false},"251":{"petle":["Rondo Kaponiera","Osiedle Kwiatowe"],"przystanki":[],"czas":13},"252":{"petle":["Rondo Kaponiera","Kacza"],"przystanki":[],"czas":16},"253":{"petle":[],"przystanki":[],"czas":false},"254":{"petle":[],"przystanki":[],"czas":false},"N21":{"petle":["Osiedle Jana III Sobieskiego","Osiedle Lecha"],"przystanki":[],"czas":34},"L":{"petle":["Port Lotniczy Ławica","Dworzec Główny"],"przystanki":[],"czas":20}}